update_checker.py
update_checker_test.py
update_checker-0.17.dist-info/LICENSE.txt
update_checker-0.17.dist-info/METADATA
update_checker-0.17.dist-info/WHEEL
update_checker-0.17.dist-info/top_level.txt
update_checker-0.17.dist-info/RECORD
