Metadata-Version: 2.1
Name: update_checker
Version: 0.17
Summary: A python module that will check for package updates.
Home-page: https://github.com/bboe/update_checker
Author: Bryce Boe
Author-email: bbzbryce@gmail.com
License: Simplified BSD License
Platform: UNKNOWN
Classifier: Intended Audience :: Developers
Classifier: License :: OSI Approved :: BSD License
Classifier: Operating System :: OS Independent
Classifier: Programming Language :: Python
Classifier: Programming Language :: Python :: 2.7
Classifier: Programming Language :: Python :: 3
Classifier: Programming Language :: Python :: 3.3
Classifier: Programming Language :: Python :: 3.4
Classifier: Programming Language :: Python :: 3.5
